sphinx_reredirects/__init__.py
sphinx_reredirects-0.1.6.dist-info/licenses/LICENSE
sphinx_reredirects-0.1.6.dist-info/METADATA
sphinx_reredirects-0.1.6.dist-info/WHEEL
sphinx_reredirects-0.1.6.dist-info/top_level.txt
sphinx_reredirects-0.1.6.dist-info/RECORD
